{
  "resource": "Players",
  "http_method": "GET",
  "route": "players?page[limit]=4",
  "description": "List players 4 at a time",
  "explanation": null,
  "parameters": [

  ],
  "response_fields": [

  ],
  "requests": [
    {
      "request_method": "GET",
      "request_path": "players?page[limit]=4",
      "request_body": null,
      "request_headers": {
        "Content-Type": "application/vnd.api+json"
      },
      "request_query_parameters": {
        "page": {
          "limit": "4"
        }
      },
      "request_content_type": "application/vnd.api+json",
      "response_status": 200,
      "response_status_text": "OK",
      "response_body": "{\"data\":[{\"id\":\"661\",\"type\":\"players\",\"links\":{\"self\":\"http://example.org/players/661\"},\"attributes\":{\"created-at\":\"2015-07-27T15:00:12.835Z\",\"updated-at\":\"2015-07-27T15:00:12.835Z\",\"name\":\"Kid 0\"},\"relationships\":{\"matches\":{\"links\":{\"self\":\"http://example.org/players/661/relationships/matches\",\"related\":\"http://example.org/players/661/matches\"}}}},{\"id\":\"662\",\"type\":\"players\",\"links\":{\"self\":\"http://example.org/players/662\"},\"attributes\":{\"created-at\":\"2015-07-27T15:00:12.837Z\",\"updated-at\":\"2015-07-27T15:00:12.837Z\",\"name\":\"Kid 1\"},\"relationships\":{\"matches\":{\"links\":{\"self\":\"http://example.org/players/662/relationships/matches\",\"related\":\"http://example.org/players/662/matches\"}}}},{\"id\":\"663\",\"type\":\"players\",\"links\":{\"self\":\"http://example.org/players/663\"},\"attributes\":{\"created-at\":\"2015-07-27T15:00:12.838Z\",\"updated-at\":\"2015-07-27T15:00:12.838Z\",\"name\":\"Kid 2\"},\"relationships\":{\"matches\":{\"links\":{\"self\":\"http://example.org/players/663/relationships/matches\",\"related\":\"http://example.org/players/663/matches\"}}}},{\"id\":\"664\",\"type\":\"players\",\"links\":{\"self\":\"http://example.org/players/664\"},\"attributes\":{\"created-at\":\"2015-07-27T15:00:12.840Z\",\"updated-at\":\"2015-07-27T15:00:12.840Z\",\"name\":\"Kid 3\"},\"relationships\":{\"matches\":{\"links\":{\"self\":\"http://example.org/players/664/relationships/matches\",\"related\":\"http://example.org/players/664/matches\"}}}}],\"meta\":{\"record-count\":5},\"links\":{\"first\":\"http://example.org/players?page%5Blimit%5D=4\\u0026page%5Boffset%5D=0\",\"next\":\"http://example.org/players?page%5Blimit%5D=4\\u0026page%5Boffset%5D=4\",\"last\":\"http://example.org/players?page%5Blimit%5D=4\\u0026page%5Boffset%5D=1\"}}",
      "response_headers": {
        "Content-Type": "application/vnd.api+json"
      },
      "response_content_type": "application/vnd.api+json",
      "curl": null
    }
  ]
}